eacy/__init__.py
eacy/collate_params.py
eacy-1.0.1.dist-info/METADATA
eacy-1.0.1.dist-info/WHEEL
eacy-1.0.1.dist-info/top_level.txt
eacy-1.0.1.dist-info/RECORD
